django_custom_admin_pages/__init__.py
django_custom_admin_pages/admin.py
django_custom_admin_pages/apps.py
django_custom_admin_pages/default_settings.py
django_custom_admin_pages/exceptions.py
django_custom_admin_pages/templates/base_custom_admin.html
django_custom_admin_pages/urls.py
django_custom_admin_pages/views/__init__.py
django_custom_admin_pages/views/admin_base_view.py
django_custom_admin_pages-1.2.7.dist-info/LICENSE
django_custom_admin_pages-1.2.7.dist-info/METADATA
django_custom_admin_pages-1.2.7.dist-info/WHEEL
django_custom_admin_pages-1.2.7.dist-info/RECORD
