Metadata-Version: 2.1
Name: django-custom-admin-pages
Version: 1.2.7
Summary: A django app that lets you add standard class-based views to the django admin index and navigation.
Home-page: https://github.com/lekjos/django-custom-admin-pages
License: BSD-3-Clause
Keywords: django,admin,django-admin,django admin,interface,customize admin,custom admin,customize
Author: Leif Kjos
Author-email: leif+pypi@leifkjos.com
Maintainer: Leif Kjos
Maintainer-email: leif+pypi@leifkjos.com
Requires-Python: >=3.8,<4.0
Classifier: Development Status :: 5 - Production/Stable
Classifier: Environment :: Web Environment
Classifier: Framework :: Django
Classifier: Framework :: Django :: 3.2
Classifier: Framework :: Django :: 4.0
Classifier: Framework :: Django :: 4.1
Classifier: Framework :: Django :: 4.2
Classifier: Framework :: Django :: 5.0
Classifier: Framework :: Django :: 5.1
Classifier: Framework :: Django :: 5.2
Classifier: Intended Audience :: Developers
Classifier: License :: OSI Approved :: BSD License
Classifier: Operating System :: OS Independent
Classifier: Programming Language :: Python
Classifier: Programming Language :: Python :: 3
Classifier: Programming Language :: Python :: 3.8
Classifier: Programming Language :: Python :: 3.9
Classifier: Programming Language :: Python :: 3.10
Classifier: Programming Language :: Python :: 3.11
Classifier: Programming Language :: Python :: 3.12
Classifier: Programming Language :: Python :: 3.13
Classifier: Programming Language :: Python :: 3.14
Classifier: Topic :: Software Development :: Libraries :: Application Frameworks
Classifier: Topic :: Software Development :: Libraries :: Python Modules
Requires-Dist: django (>=3.2)
Project-URL: Repository, https://github.com/lekjos/django-custom-admin-pages
